qytPython/__init__.py
qytPython/tools/__init__.py
qytPython/tools/file.py
qytPython/tools/file_csv.py
qytPython/tools/ftp.py
qytPython/tools/text.py
qytPython-0.0.3.dist-info/LICENSE
qytPython-0.0.3.dist-info/METADATA
qytPython-0.0.3.dist-info/WHEEL
qytPython-0.0.3.dist-info/top_level.txt
qytPython-0.0.3.dist-info/RECORD
