Metadata-Version: 2.1
Name: qytPython
Version: 0.0.3
Summary: qytPython: Python tools
Home-page: https://github.com/q759729997/qytPython
Author: qiaoyongtian
License: Apache License
Platform: UNKNOWN
Requires-Python: >=3.6
Requires-Dist: PyYAML
